MANIFEST.in
README.txt
setup.cfg
setup.py
docs/HISTORY.txt
horae/__init__.py
horae.layout.egg-info/PKG-INFO
horae.layout.egg-info/SOURCES.txt
horae.layout.egg-info/dependency_links.txt
horae.layout.egg-info/entry_points.txt
horae.layout.egg-info/namespace_packages.txt
horae.layout.egg-info/not-zip-safe
horae.layout.egg-info/requires.txt
horae.layout.egg-info/top_level.txt
horae/layout/__init__.py
horae/layout/configure.zcml
horae/layout/interfaces.py
horae/layout/layout.py
horae/layout/navigation.py
horae/layout/objects.py
horae/layout/overrides.zcml
horae/layout/resource.py
horae/layout/soupselect.py
horae/layout/table.py
horae/layout/viewlets.py
horae/layout/views.py
horae/layout/widgets.py
horae/layout/locales/horae.layout.pot
horae/layout/locales/de/LC_MESSAGES/horae.layout.mo
horae/layout/locales/de/LC_MESSAGES/horae.layout.po
horae/layout/static/collapsible.js
horae/layout/static/deco.css
horae/layout/static/dialogs.js
horae/layout/static/editor.css
horae/layout/static/form.css
horae/layout/static/hash.js
horae/layout/static/hours.js
horae/layout/static/i18n.js
horae/layout/static/initialization.js
horae/layout/static/jqplot.css
horae/layout/static/listing.css
horae/layout/static/listing.js
horae/layout/static/loader-large.gif
horae/layout/static/loader-small.gif
horae/layout/static/nestedlist.css
horae/layout/static/nestedlist.js
horae/layout/static/reset.css
horae/layout/static/search.js
horae/layout/static/style.css
horae/layout/static/ticketing.js
horae/layout/static/typography.css
horae/layout/static/uitheme/jquery-ui.css
horae/layout/static/uitheme/images/ui-bg_flat_0_669966_40x100.png
horae/layout/static/uitheme/images/ui-bg_flat_0_996666_40x100.png
horae/layout/static/uitheme/images/ui-bg_flat_0_ffffff_40x100.png
horae/layout/static/uitheme/images/ui-bg_flat_100_eeeeee_40x100.png
horae/layout/static/uitheme/images/ui-bg_flat_100_ffffff_40x100.png
horae/layout/static/uitheme/images/ui-bg_flat_15_2b2922_40x100.png
horae/layout/static/uitheme/images/ui-bg_highlight-hard_15_447744_1x100.png
horae/layout/static/uitheme/images/ui-bg_highlight-hard_95_cccccc_1x100.png
horae/layout/static/uitheme/images/ui-bg_highlight-soft_25_225522_1x100.png
horae/layout/static/uitheme/images/ui-icons_114411_256x240.png
